LICENSE
README.md
setup.py
sep241/__init__.py
sep241/sep241covariance.py
sep241/sep241deconvolve.py
sep241/sep241events.py
sep241/sep241latent.py
sep241/sep241mkbw.py
sep241/sep241mkdt.py
sep241/sep241model.py
sep241/sep241peakcalling.py
sep241/sep241prep.py
sep241/sep241util.py
sep241.egg-info/PKG-INFO
sep241.egg-info/SOURCES.txt
sep241.egg-info/dependency_links.txt
sep241.egg-info/entry_points.txt
sep241.egg-info/requires.txt
sep241.egg-info/top_level.txt