Metadata-Version: 2.1
Name: sep241
Version: 0.4.3
Summary: Deconvolve CUT&Tag 2for1 data.
Home-page: https://github.com/settylab/2for1separator
Author: Setty Lab
Author-email: msetty@fredhutch.org
License: GNU General Public License v3.0
Platform: UNKNOWN
Classifier: Development Status :: 4 - Beta
Classifier: Intended Audience :: Science/Research
Classifier: License :: OSI Approved :: GNU General Public License v3 (GPLv3)
Classifier: Operating System :: POSIX :: Linux
Classifier: Programming Language :: Python :: 3.9
Classifier: Programming Language :: Python :: 3.10
License-File: LICENSE
